[{"set":"A1","number":1,"rarity":"C","name":"Bulbasaur","packs":["Mewtwo"]},{"set":"A1","number":2,"rarity":"U","name":"Ivysaur","packs":["Mewtwo"]},{"set":"A1","number":3,"rarity":"R","name":"Venusaur","packs":["Mewtwo"]},{"set":"A1","number":4,"rarity":"RR","name":"Venusaur ex","packs":["Mewtwo"]},{"set":"A1","number":5,"rarity":"C","name":"Caterpie","packs":["Pikachu"]},{"set":"A1","number":6,"rarity":"C","name":"Metapod","packs":["Pikachu"]},{"set":"A1","number":7,"rarity":"R","name":"Butterfree","packs":["Pikachu"]},{"set":"A1","number":8,"rarity":"C","name":"Weedle","packs":["Mewtwo"]},{"set":"A1","number":9,"rarity":"C","name":"Kakuna","packs":["Mewtwo"]},{"set":"A1","number":10,"rarity":"R","name":"Beedrill","packs":["Mewtwo"]},{"set":"A1","number":11,"rarity":"C","name":"Oddish","packs":["Charizard"]},{"set":"A1","number":12,"rarity":"U","name":"Gloom","packs":["Charizard"]},{"set":"A1","number":13,"rarity":"R","name":"Vileplume","packs":["Charizard"]},{"set":"A1","number":14,"rarity":"C","name":"Paras","packs":["Pikachu"]},{"set":"A1","number":15,"rarity":"U","name":"Parasect","packs":["Pikachu"]},{"set":"A1","number":16,"rarity":"C","name":"Venonat","packs":["Mewtwo"]},{"set":"A1","number":17,"rarity":"U","name":"Venomoth","packs":["Mewtwo"]},{"set":"A1","number":18,"rarity":"C","name":"Bellsprout","packs":["Charizard"]},{"set":"A1","number":19,"rarity":"U","name":"Weepinbell","packs":["Charizard"]},{"set":"A1","number":20,"rarity":"R","name":"Victreebel","packs":["Charizard"]},{"set":"A1","number":21,"rarity":"C","name":"Exeggcute","packs":["Charizard"]},{"set":"A1","number":22,"rarity":"R","name":"Exeggutor","packs":["Charizard"]},{"set":"A1","number":23,"rarity":"RR","name":"Exeggutor ex","packs":["Charizard"]},{"set":"A1","number":24,"rarity":"C","name":"Tangela","packs":["Charizard"]},{"set":"A1","number":25,"rarity":"C","name":"Scyther","packs":["Mewtwo"]},{"set":"A1","number":26,"rarity":"U","name":"Pinsir","packs":["Charizard","Mewtwo","Pikachu"]},{"set":"A1","number":27,"rarity":"C","name":"Cottonee","packs":["Charizard","Mewtwo","Pikachu"]},{"set":"A1","number":28,"rarity":"U","name":"Whimsicott","packs":["Charizard","Mewtwo","Pikachu"]},{"set":"A1","number":29,"rarity":"C","name":"Petilil","packs":["Charizard","Mewtwo","Pikachu"]},{"set":"A1","number":30,"rarity":"U","name":"Lilligant","packs":["Charizard","Mewtwo","Pikachu"]},{"set":"A1","number":31,"rarity":"C","name":"Skiddo","packs":["Charizard"]},{"set":"A1","number":32,"rarity":"C","name":"Gogoat","packs":["Charizard"]},{"set":"A1","number":33,"rarity":"C","name":"Charmander","packs":["Charizard"]},{"set":"A1","number":34,"rarity":"U","name":"Charmeleon","packs":["Charizard"]},{"set":"A1","number":35,"rarity":"R","name":"Charizard","packs":["Charizard"]},{"set":"A1","number":36,"rarity":"RR","name":"Charizard ex","packs":["Charizard"]},{"set":"A1","number":37,"rarity":"C","name":"Vulpix","packs":["Charizard"]},{"set":"A1","number":38,"rarity":"U","name":"Ninetales","packs":["Charizard"]},{"set":"A1","number":39,"rarity":"C","name":"Growlithe","packs":["Pikachu"]},{"set":"A1","number":40,"rarity":"R","name":"Arcanine","packs":["Pikachu"]},{"set":"A1","number":41,"rarity":"RR","name":"Arcanine ex","packs":["Pikachu"]},{"set":"A1","number":42,"rarity":"C","name":"Ponyta","packs":["Charizard","Mewtwo","Pikachu"]},{"set":"A1","number":43,"rarity":"U","name":"Rapidash","packs":["Charizard","Mewtwo","Pikachu"]},{"set":"A1","number":44,"rarity":"C","name":"Magmar","packs":["Charizard"]},{"set":"A1","number":45,"rarity":"R","name":"Flareon","packs":["Charizard"]},{"set":"A1","number":46,"rarity":"R","name":"Moltres","packs":["Charizard"]},{"set":"A1","number":47,"rarity":"RR","name":"Moltres ex","packs":["Charizard"]},{"set":"A1","number":48,"rarity":"C","name":"Heatmor","packs":["Charizard","Mewtwo","Pikachu"]},{"set":"A1","number":49,"rarity":"C","name":"Salandit","packs":["Mewtwo"]},{"set":"A1","number":50,"rarity":"C","name":"Salazzle","packs":["Mewtwo"]},{"set":"A1","number":51,"rarity":"C","name":"Sizzlipede","packs":["Charizard","Mewtwo","Pikachu"]},{"set":"A1","number":52,"rarity":"U","name":"Centiskorch","packs":["Charizard","Mewtwo","Pikachu"]},{"set":"A1","number":53,"rarity":"C","name":"Squirtle","packs":["Pikachu"]},{"set":"A1","number":54,"rarity":"U","name":"Wartortle","packs":["Pikachu"]},{"set":"A1","number":55,"rarity":"R","name":"Blastoise","packs":["Pikachu"]},{"set":"A1","number":56,"rarity":"RR","name":"Blastoise ex","packs":["Pikachu"]},{"set":"A1","number":57,"rarity":"C","name":"Psyduck","packs":["Charizard","Mewtwo","Pikachu"]},{"set":"A1","number":58,"rarity":"U","name":"Golduck","packs":["Charizard","Mewtwo","Pikachu"]},{"set":"A1","number":59,"rarity":"C","name":"Poliwag","packs":["Charizard"]},{"set":"A1","number":60,"rarity":"U","name":"Poliwhirl","packs":["Charizard"]},{"set":"A1","number":61,"rarity":"R","name":"Poliwrath","packs":["Charizard"]},{"set":"A1","number":62,"rarity":"C","name":"Tentacool","packs":["Mewtwo"]},{"set":"A1","number":63,"rarity":"U","name":"Tentacruel","packs":["Mewtwo"]},{"set":"A1","number":64,"rarity":"C","name":"Seel","packs":["Pikachu"]},{"set":"A1","number":65,"rarity":"U","name":"Dewgong","packs":["Pikachu"]},{"set":"A1","number":66,"rarity":"C","name":"Shellder","packs":["Mewtwo"]},{"set":"A1","number":67,"rarity":"U","name":"Cloyster","packs":["Mewtwo"]},{"set":"A1","number":68,"rarity":"C","name":"Krabby","packs":["Mewtwo"]},{"set":"A1","number":69,"rarity":"U","name":"Kingler","packs":["Mewtwo"]},{"set":"A1","number":70,"rarity":"C","name":"Horsea","packs":["Pikachu"]},{"set":"A1","number":71,"rarity":"U","name":"Seadra","packs":["Pikachu"]},{"set":"A1","number":72,"rarity":"C","name":"Goldeen","packs":["Pikachu"]},{"set":"A1","number":73,"rarity":"C","name":"Seaking","packs":["Pikachu"]},{"set":"A1","number":74,"rarity":"C","name":"Staryu","packs":["Charizard"]},{"set":"A1","number":75,"rarity":"U","name":"Starmie","packs":["Charizard"]},{"set":"A1","number":76,"rarity":"RR","name":"Starmie ex","packs":["Charizard"]},{"set":"A1","number":77,"rarity":"C","name":"Magikarp","packs":["Pikachu"]},{"set":"A1","number":78,"rarity":"R","name":"Gyarados","packs":["Pikachu"]},{"set":"A1","number":79,"rarity":"R","name":"Lapras","packs":["Charizard"]},{"set":"A1","number":80,"rarity":"R","name":"Vaporeon","packs":["Mewtwo"]},{"set":"A1","number":81,"rarity":"U","name":"Omanyte","packs":["Pikachu"]},{"set":"A1","number":82,"rarity":"R","name":"Omastar","packs":["Pikachu"]},{"set":"A1","number":83,"rarity":"R","name":"Articuno","packs":["Mewtwo"]},{"set":"A1","number":84,"rarity":"RR","name":"Articuno ex","packs":["Mewtwo"]},{"set":"A1","number":85,"rarity":"C","name":"Ducklett","packs":["Charizard"]},{"set":"A1","number":86,"rarity":"U","name":"Swanna","packs":["Charizard"]},{"set":"A1","number":87,"rarity":"C","name":"Froakie","packs":["Charizard"]},{"set":"A1","number":88,"rarity":"U","name":"Frogadier","packs":["Charizard"]},{"set":"A1","number":89,"rarity":"R","name":"Greninja","packs":["Charizard"]},{"set":"A1","number":90,"rarity":"C","name":"Pyukumuku","packs":["Charizard"]},{"set":"A1","number":91,"rarity":"U","name":"Bruxish","packs":["Charizard","Mewtwo","Pikachu"]},{"set":"A1","number":92,"rarity":"C","name":"Snom","packs":["Charizard","Mewtwo","Pikachu"]},{"set":"A1","number":93,"rarity":"U","name":"Frosmoth","packs":["Charizard","Mewtwo","Pikachu"]},{"set":"A1","number":94,"rarity":"C","name":"Pikachu","packs":["Pikachu"]},{"set":"A1","number":95,"rarity":"R","name":"Raichu","packs":["Pikachu"]},{"set":"A1","number":96,"rarity":"RR","name":"Pikachu ex","packs":["Pikachu"]},{"set":"A1","number":97,"rarity":"C","name":"Magnemite","packs":["Pikachu"]},{"set":"A1","number":98,"rarity":"R","name":"Magneton","packs":["Pikachu"]},{"set":"A1","number":99,"rarity":"C","name":"Voltorb","packs":["Pikachu"]},{"set":"A1","number":100,"rarity":"U","name":"Electrode","packs":["Pikachu"]},{"set":"A1","number":101,"rarity":"C","name":"Electabuzz","packs":["Pikachu"]},{"set":"A1","number":102,"rarity":"R","name":"Jolteon","packs":["Pikachu"]},{"set":"A1","number":103,"rarity":"R","name":"Zapdos","packs":["Pikachu"]},{"set":"A1","number":104,"rarity":"RR","name":"Zapdos ex","packs":["Pikachu"]},{"set":"A1","number":105,"rarity":"C","name":"Blitzle","packs":["Charizard","Mewtwo","Pikachu"]},{"set":"A1","number":106,"rarity":"U","name":"Zebstrika","packs":["Charizard","Mewtwo","Pikachu"]},{"set":"A1","number":107,"rarity":"C","name":"Tynamo","packs":["Mewtwo"]},{"set":"A1","number":108,"rarity":"U","name":"Eelektrik","packs":["Mewtwo"]},{"set":"A1","number":109,"rarity":"R","name":"Eelektross","packs":["Mewtwo"]},{"set":"A1","number":110,"rarity":"C","name":"Helioptile","packs":["Charizard","Mewtwo","Pikachu"]},{"set":"A1","number":111,"rarity":"C","name":"Heliolisk","packs":["Charizard","Mewtwo","Pikachu"]},{"set":"A1","number":112,"rarity":"U","name":"Pincurchin","packs":["Charizard","Mewtwo","Pikachu"]},{"set":"A1","number":113,"rarity":"C","name":"Clefairy","packs":["Pikachu"]},{"set":"A1","number":114,"rarity":"U","name":"Clefable","packs":["Pikachu"]},{"set":"A1","number":115,"rarity":"C","name":"Abra","packs":["Charizard"]},{"set":"A1","number":116,"rarity":"U","name":"Kadabra","packs":["Charizard"]},{"set":"A1","number":117,"rarity":"R","name":"Alakazam","packs":["Charizard"]},{"set":"A1","number":118,"rarity":"C","name":"Slowpoke","packs":["Charizard","Mewtwo","Pikachu"]},{"set":"A1","number":119,"rarity":"U","name":"Slowbro","packs":["Charizard","Mewtwo","Pikachu"]},{"set":"A1","number":120,"rarity":"C","name":"Gastly","packs":["Mewtwo"]},{"set":"A1","number":121,"rarity":"U","name":"Haunter","packs":["Mewtwo"]},{"set":"A1","number":122,"rarity":"R","name":"Gengar","packs":["Mewtwo"]},{"set":"A1","number":123,"rarity":"RR","name":"Gengar ex","packs":["Mewtwo"]},{"set":"A1","number":124,"rarity":"C","name":"Drowzee","packs":["Pikachu"]},{"set":"A1","number":125,"rarity":"R","name":"Hypno","packs":["Pikachu"]},{"set":"A1","number":126,"rarity":"U","name":"Mr. Mime","packs":["Mewtwo"]},{"set":"A1","number":127,"rarity":"C","name":"Jynx","packs":["Mewtwo"]},{"set":"A1","number":128,"rarity":"R","name":"Mewtwo","packs":["Mewtwo"]},{"set":"A1","number":129,"rarity":"RR","name":"Mewtwo ex","packs":["Mewtwo"]},{"set":"A1","number":130,"rarity":"C","name":"Ralts","packs":["Mewtwo"]},{"set":"A1","number":131,"rarity":"U","name":"Kirlia","packs":["Mewtwo"]},{"set":"A1","number":132,"rarity":"R","name":"Gardevoir","packs":["Mewtwo"]},{"set":"A1","number":133,"rarity":"C","name":"Woobat","packs":["Charizard","Mewtwo","Pikachu"]},{"set":"A1","number":134,"rarity":"C","name":"Swoobat","packs":["Charizard","Mewtwo","Pikachu"]},{"set":"A1","number":135,"rarity":"C","name":"Golett","packs":["Charizard","Mewtwo","Pikachu"]},{"set":"A1","number":136,"rarity":"U","name":"Golurk","packs":["Charizard","Mewtwo","Pikachu"]},{"set":"A1","number":137,"rarity":"C","name":"Sandshrew","packs":["Charizard","Mewtwo","Pikachu"]},{"set":"A1","number":138,"rarity":"U","name":"Sandslash","packs":["Charizard","Mewtwo","Pikachu"]},{"set":"A1","number":139,"rarity":"C","name":"Diglett","packs":["Pikachu"]},{"set":"A1","number":140,"rarity":"U","name":"Dugtrio","packs":["Pikachu"]},{"set":"A1","number":141,"rarity":"C","name":"Mankey","packs":["Charizard"]},{"set":"A1","number":142,"rarity":"U","name":"Primeape","packs":["Charizard"]},{"set":"A1","number":143,"rarity":"C","name":"Machop","packs":["Charizard"]},{"set":"A1","number":144,"rarity":"U","name":"Machoke","packs":["Charizard"]},{"set":"A1","number":145,"rarity":"R","name":"Machamp","packs":["Charizard"]},{"set":"A1","number":146,"rarity":"RR","name":"Machamp ex","packs":["Charizard"]},{"set":"A1","number":147,"rarity":"C","name":"Geodude","packs":["Pikachu"]},{"set":"A1","number":148,"rarity":"U","name":"Graveler","packs":["Pikachu"]},{"set":"A1","number":149,"rarity":"R","name":"Golem","packs":["Pikachu"]},{"set":"A1","number":150,"rarity":"U","name":"Onix","packs":["Pikachu"]},{"set":"A1","number":151,"rarity":"C","name":"Cubone","packs":["Mewtwo"]},{"set":"A1","number":152,"rarity":"U","name":"Marowak","packs":["Mewtwo"]},{"set":"A1","number":153,"rarity":"RR","name":"Marowak ex","packs":["Mewtwo"]},{"set":"A1","number":154,"rarity":"C","name":"Hitmonlee","packs":["Mewtwo"]},{"set":"A1","number":155,"rarity":"C","name":"Hitmonchan","packs":["Charizard"]},{"set":"A1","number":156,"rarity":"C","name":"Rhyhorn","packs":["Mewtwo"]},{"set":"A1","number":157,"rarity":"U","name":"Rhydon","packs":["Mewtwo"]},{"set":"A1","number":158,"rarity":"U","name":"Kabuto","packs":["Charizard"]},{"set":"A1","number":159,"rarity":"R","name":"Kabutops","packs":["Charizard"]},{"set":"A1","number":160,"rarity":"C","name":"Mienfoo","packs":["Pikachu"]},{"set":"A1","number":161,"rarity":"U","name":"Mienshao","packs":["Pikachu"]},{"set":"A1","number":162,"rarity":"C","name":"Clobbopus","packs":["Charizard","Mewtwo","Pikachu"]},{"set":"A1","number":163,"rarity":"U","name":"Grapploct","packs":["Charizard","Mewtwo","Pikachu"]},{"set":"A1","number":164,"rarity":"C","name":"Ekans","packs":["Charizard","Mewtwo","Pikachu"]},{"set":"A1","number":165,"rarity":"U","name":"Arbok","packs":["Charizard","Mewtwo","Pikachu"]},{"set":"A1","number":166,"rarity":"C","name":"Nidoran♀","packs":["Pikachu"]},{"set":"A1","number":167,"rarity":"U","name":"Nidorina","packs":["Pikachu"]},{"set":"A1","number":168,"rarity":"R","name":"Nidoqueen","packs":["Pikachu"]},{"set":"A1","number":169,"rarity":"C","name":"Nidoran♂","packs":["Pikachu"]},{"set":"A1","number":170,"rarity":"U","name":"Nidorino","packs":["Pikachu"]},{"set":"A1","number":171,"rarity":"R","name":"Nidoking","packs":["Pikachu"]},{"set":"A1","number":172,"rarity":"C","name":"Zubat","packs":["Mewtwo"]},{"set":"A1","number":173,"rarity":"U","name":"Golbat","packs":["Mewtwo"]},{"set":"A1","number":174,"rarity":"C","name":"Grimer","packs":["Mewtwo"]},{"set":"A1","number":175,"rarity":"R","name":"Muk","packs":["Mewtwo"]},{"set":"A1","number":176,"rarity":"C","name":"Koffing","packs":["Mewtwo"]},{"set":"A1","number":177,"rarity":"R","name":"Weezing","packs":["Mewtwo"]},{"set":"A1","number":178,"rarity":"C","name":"Mawile","packs":["Charizard"]},{"set":"A1","number":179,"rarity":"C","name":"Pawniard","packs":["Charizard","Mewtwo","Pikachu"]},{"set":"A1","number":180,"rarity":"U","name":"Bisharp","packs":["Charizard","Mewtwo","Pikachu"]},{"set":"A1","number":181,"rarity":"C","name":"Meltan","packs":["Charizard"]},{"set":"A1","number":182,"rarity":"R","name":"Melmetal","packs":["Charizard"]},{"set":"A1","number":183,"rarity":"C","name":"Dratini","packs":["Mewtwo"]},{"set":"A1","number":184,"rarity":"U","name":"Dragonair","packs":["Mewtwo"]},{"set":"A1","number":185,"rarity":"R","name":"Dragonite","packs":["Mewtwo"]},{"set":"A1","number":186,"rarity":"C","name":"Pidgey","packs":["Mewtwo"]},{"set":"A1","number":187,"rarity":"C","name":"Pidgeotto","packs":["Mewtwo"]},{"set":"A1","number":188,"rarity":"R","name":"Pidgeot","packs":["Mewtwo"]},{"set":"A1","number":189,"rarity":"C","name":"Rattata","packs":["Charizard","Mewtwo","Pikachu"]},{"set":"A1","number":190,"rarity":"C","name":"Raticate","packs":["Charizard","Mewtwo","Pikachu"]},{"set":"A1","number":191,"rarity":"C","name":"Spearow","packs":["Charizard"]},{"set":"A1","number":192,"rarity":"C","name":"Fearow","packs":["Charizard"]},{"set":"A1","number":193,"rarity":"C","name":"Jigglypuff","packs":["Pikachu"]},{"set":"A1","number":194,"rarity":"C","name":"Wigglytuff","packs":["Pikachu"]},{"set":"A1","number":195,"rarity":"RR","name":"Wigglytuff ex","packs":["Pikachu"]},{"set":"A1","number":196,"rarity":"C","name":"Meowth","packs":["Charizard"]},{"set":"A1","number":197,"rarity":"U","name":"Persian","packs":["Charizard"]},{"set":"A1","number":198,"rarity":"C","name":"Farfetch’d","packs":["Charizard","Mewtwo","Pikachu"]},{"set":"A1","number":199,"rarity":"C","name":"Doduo","packs":["Charizard","Mewtwo","Pikachu"]},{"set":"A1","number":200,"rarity":"U","name":"Dodrio","packs":["Charizard","Mewtwo","Pikachu"]},{"set":"A1","number":201,"rarity":"U","name":"Lickitung","packs":["Mewtwo"]},{"set":"A1","number":202,"rarity":"U","name":"Chansey","packs":["Pikachu"]},{"set":"A1","number":203,"rarity":"R","name":"Kangaskhan","packs":["Charizard"]},{"set":"A1","number":204,"rarity":"U","name":"Tauros","packs":["Charizard"]},{"set":"A1","number":205,"rarity":"R","name":"Ditto","packs":["Mewtwo"]},{"set":"A1","number":206,"rarity":"C","name":"Eevee","packs":["Charizard"]},{"set":"A1","number":207,"rarity":"C","name":"Eevee","packs":["Mewtwo"]},{"set":"A1","number":208,"rarity":"C","name":"Eevee","packs":["Pikachu"]},{"set":"A1","number":209,"rarity":"U","name":"Porygon","packs":["Mewtwo"]},{"set":"A1","number":210,"rarity":"R","name":"Aerodactyl","packs":["Mewtwo"]},{"set":"A1","number":211,"rarity":"R","name":"Snorlax","packs":["Pikachu"]},{"set":"A1","number":212,"rarity":"C","name":"Minccino","packs":["Charizard","Mewtwo","Pikachu"]},{"set":"A1","number":213,"rarity":"U","name":"Cinccino","packs":["Charizard","Mewtwo","Pikachu"]},{"set":"A1","number":214,"rarity":"C","name":"Wooloo","packs":["Charizard","Mewtwo","Pikachu"]},{"set":"A1","number":215,"rarity":"C","name":"Dubwool","packs":["Charizard","Mewtwo","Pikachu"]},{"set":"A1","number":216,"rarity":"C","name":"Helix Fossil","packs":["Pikachu"]},{"set":"A1","number":217,"rarity":"C","name":"Dome Fossil","packs":["Charizard"]},{"set":"A1","number":218,"rarity":"C","name":"Old Amber","packs":["Mewtwo"]},{"set":"A1","number":219,"rarity":"U","name":"Erika","packs":["Charizard"]},{"set":"A1","number":220,"rarity":"U","name":"Misty","packs":["Pikachu"]},{"set":"A1","number":221,"rarity":"U","name":"Blaine","packs":["Charizard"]},{"set":"A1","number":222,"rarity":"U","name":"Koga","packs":["Mewtwo"]},{"set":"A1","number":223,"rarity":"U","name":"Giovanni","packs":["Mewtwo"]},{"set":"A1","number":224,"rarity":"U","name":"Brock","packs":["Pikachu"]},{"set":"A1","number":225,"rarity":"U","name":"Sabrina","packs":["Charizard"]},{"set":"A1","number":226,"rarity":"U","name":"Lt. Surge","packs":["Pikachu"]},{"set":"A1","number":227,"rarity":"AR","name":"Bulbasaur","packs":["Mewtwo"]},{"set":"A1","number":228,"rarity":"AR","name":"Gloom","packs":["Charizard"]},{"set":"A1","number":229,"rarity":"AR","name":"Pinsir","packs":["Charizard"]},{"set":"A1","number":230,"rarity":"AR","name":"Charmander","packs":["Charizard"]},{"set":"A1","number":231,"rarity":"AR","name":"Rapidash","packs":["Charizard"]},{"set":"A1","number":232,"rarity":"AR","name":"Squirtle","packs":["Pikachu"]},{"set":"A1","number":233,"rarity":"AR","name":"Gyarados","packs":["Pikachu"]},{"set":"A1","number":234,"rarity":"AR","name":"Lapras","packs":["Charizard"]},{"set":"A1","number":235,"rarity":"AR","name":"Electrode","packs":["Pikachu"]},{"set":"A1","number":236,"rarity":"AR","name":"Alakazam","packs":["Charizard"]},{"set":"A1","number":237,"rarity":"AR","name":"Slowpoke","packs":["Charizard"]},{"set":"A1","number":238,"rarity":"AR","name":"Diglett","packs":["Pikachu"]},{"set":"A1","number":239,"rarity":"AR","name":"Cubone","packs":["Mewtwo"]},{"set":"A1","number":240,"rarity":"AR","name":"Nidoqueen","packs":["Pikachu"]},{"set":"A1","number":241,"rarity":"AR","name":"Nidoking","packs":["Pikachu"]},{"set":"A1","number":242,"rarity":"AR","name":"Golbat","packs":["Mewtwo"]},{"set":"A1","number":243,"rarity":"AR","name":"Weezing","packs":["Mewtwo"]},{"set":"A1","number":244,"rarity":"AR","name":"Dragonite","packs":["Mewtwo"]},{"set":"A1","number":245,"rarity":"AR","name":"Pidgeot","packs":["Mewtwo"]},{"set":"A1","number":246,"rarity":"AR","name":"Meowth","packs":["Charizard"]},{"set":"A1","number":247,"rarity":"AR","name":"Ditto","packs":["Mewtwo"]},{"set":"A1","number":248,"rarity":"AR","name":"Eevee","packs":["Pikachu"]},{"set":"A1","number":249,"rarity":"AR","name":"Porygon","packs":["Mewtwo"]},{"set":"A1","number":250,"rarity":"AR","name":"Snorlax","packs":["Pikachu"]},{"set":"A1","number":251,"rarity":"SR","name":"Venusaur ex","packs":["Mewtwo"]},{"set":"A1","number":252,"rarity":"SR","name":"Exeggutor ex","packs":["Charizard"]},{"set":"A1","number":253,"rarity":"SR","name":"Charizard ex","packs":["Charizard"]},{"set":"A1","number":254,"rarity":"SR","name":"Arcanine ex","packs":["Pikachu"]},{"set":"A1","number":255,"rarity":"SR","name":"Moltres ex","packs":["Charizard"]},{"set":"A1","number":256,"rarity":"SR","name":"Blastoise ex","packs":["Pikachu"]},{"set":"A1","number":257,"rarity":"SR","name":"Starmie ex","packs":["Charizard"]},{"set":"A1","number":258,"rarity":"SR","name":"Articuno ex","packs":["Mewtwo"]},{"set":"A1","number":259,"rarity":"SR","name":"Pikachu ex","packs":["Pikachu"]},{"set":"A1","number":260,"rarity":"SR","name":"Zapdos ex","packs":["Pikachu"]},{"set":"A1","number":261,"rarity":"SR","name":"Gengar ex","packs":["Mewtwo"]},{"set":"A1","number":262,"rarity":"SR","name":"Mewtwo ex","packs":["Mewtwo"]},{"set":"A1","number":263,"rarity":"SR","name":"Machamp ex","packs":["Charizard"]},{"set":"A1","number":264,"rarity":"SR","name":"Marowak ex","packs":["Mewtwo"]},{"set":"A1","number":265,"rarity":"SR","name":"Wigglytuff ex","packs":["Pikachu"]},{"set":"A1","number":266,"rarity":"SR","name":"Erika","packs":["Charizard"]},{"set":"A1","number":267,"rarity":"SR","name":"Misty","packs":["Pikachu"]},{"set":"A1","number":268,"rarity":"SR","name":"Blaine","packs":["Charizard"]},{"set":"A1","number":269,"rarity":"SR","name":"Koga","packs":["Mewtwo"]},{"set":"A1","number":270,"rarity":"SR","name":"Giovanni","packs":["Mewtwo"]},{"set":"A1","number":271,"rarity":"SR","name":"Brock","packs":["Pikachu"]},{"set":"A1","number":272,"rarity":"SR","name":"Sabrina","packs":["Charizard"]},{"set":"A1","number":273,"rarity":"SR","name":"Lt. Surge","packs":["Pikachu"]},{"set":"A1","number":274,"rarity":"SAR","name":"Moltres ex","packs":["Charizard"]},{"set":"A1","number":275,"rarity":"SAR","name":"Articuno ex","packs":["Mewtwo"]},{"set":"A1","number":276,"rarity":"SAR","name":"Zapdos ex","packs":["Pikachu"]},{"set":"A1","number":277,"rarity":"SAR","name":"Gengar ex","packs":["Mewtwo"]},{"set":"A1","number":278,"rarity":"SAR","name":"Machamp ex","packs":["Charizard"]},{"set":"A1","number":279,"rarity":"SAR","name":"Wigglytuff ex","packs":["Pikachu"]},{"set":"A1","number":280,"rarity":"IM","name":"Charizard ex","packs":["Charizard"]},{"set":"A1","number":281,"rarity":"IM","name":"Pikachu ex","packs":["Pikachu"]},{"set":"A1","number":282,"rarity":"IM","name":"Mewtwo ex","packs":["Mewtwo"]},{"set":"A1","number":283,"rarity":"IM","name":"Mew"},{"set":"A1","number":284,"rarity":"UR","name":"Charizard ex","packs":["Charizard","Mewtwo","Pikachu"]},{"set":"A1","number":285,"rarity":"UR","name":"Pikachu ex","packs":["Charizard","Mewtwo","Pikachu"]},{"set":"A1","number":286,"rarity":"UR","name":"Mewtwo ex","packs":["Charizard","Mewtwo","Pikachu"]}]